Metadata-Version: 2.1
Name: odoo-addon-product-custom-info
Version: 15.0.1.0.1.5
Summary: Add custom field in products
Home-page: https://github.com/OCA/product-attribute
Author: Tecnativa, Odoo Community Association (OCA)
Author-email: support@odoo-community.org
License: LGPL-3
Platform: UNKNOWN
Classifier: Programming Language :: Python
Classifier: Framework :: Odoo
Classifier: Framework :: Odoo :: 15.0
Classifier: License :: OSI Approved :: GNU Lesser General Public License v3 (LGPLv3)
Requires-Python: >=3.8
Requires-Dist: odoo-addon-base-custom-info <15.1dev,>=15.0dev
Requires-Dist: odoo <15.1dev,>=15.0a
